sdclientapi/__init__.py
sdclientapi/sdlocalobjects.py
securedrop_sdk-0.0.13.dist-info/LICENSE
securedrop_sdk-0.0.13.dist-info/METADATA
securedrop_sdk-0.0.13.dist-info/WHEEL
securedrop_sdk-0.0.13.dist-info/top_level.txt
securedrop_sdk-0.0.13.dist-info/RECORD
