Metadata-Version: 2.1
Name: securedrop-sdk
Version: 0.0.13
Summary: Python client API to access SecureDrop Journalist REST API
Home-page: https://github.com/freedomofpress/securedrop-sdk
Author: Freedom of the Press Foundation
Author-email: securedrop@freedom.press
License: GPLv3+
Platform: UNKNOWN
Classifier: Development Status :: 3 - Alpha
Classifier: Programming Language :: Python :: 3
Classifier: Topic :: Software Development :: Libraries :: Python Modules
Classifier: License :: OSI Approved :: GNU General Public License v3 or later (GPLv3+)
Classifier: Intended Audience :: Developers
Classifier: Operating System :: OS Independent
Requires-Python: >=3.5
Requires-Dist: requests
Requires-Dist: urllib3
